tyxe/__init__.py
tyxe/bnn.py
tyxe/guides.py
tyxe/likelihoods.py
tyxe/priors.py
tyxe/util.py
tyxe/poutine/__init__.py
tyxe/poutine/handlers.py
tyxe/poutine/reparameterization_messengers.py
tyxe/poutine/selective_messengers.py
tyxe-0.0.2.dist-info/LICENSE.md
tyxe-0.0.2.dist-info/METADATA
tyxe-0.0.2.dist-info/WHEEL
tyxe-0.0.2.dist-info/top_level.txt
tyxe-0.0.2.dist-info/RECORD
