Metadata-Version: 2.1
Name: tyxe
Version: 0.0.2
Summary: BNNs for PyTorch using Pyro
Home-page: https://github.com/emaballarin/TyXe
Author: ['Hippolyt Ritter', 'Theofanis Karaletsos']
Author-email: j.ritter@cs.ucl.ac.uk
License: MIT
Keywords: Deep Learning,Machine Learning,Bayesian Deep Learning
Classifier: Development Status :: 4 - Beta
Classifier: Topic :: Scientific/Engineering :: Artificial Intelligence
Classifier: Environment :: Console
Classifier: Programming Language :: Python :: 3
Classifier: License :: OSI Approved :: MIT License
Requires-Python: >=3.8
License-File: LICENSE.md
Requires-Dist: torch (>=1.13.1)
Requires-Dist: torchvision (>=0.14)
Requires-Dist: pyro-ppl (>=1.8.1)
